ncBuilder/__init__.py
ncBuilder/ncBuilder.py
ncBuilder/ncHelper.py
ncBuilder-0.1.0.dist-info/LICENSE.txt
ncBuilder-0.1.0.dist-info/METADATA
ncBuilder-0.1.0.dist-info/WHEEL
ncBuilder-0.1.0.dist-info/top_level.txt
ncBuilder-0.1.0.dist-info/RECORD
