Metadata-Version: 2.1
Name: ncBuilder
Version: 0.1.0
Summary: ncBuilder
Home-page: https://github.com/Eksoss/ncBuilder
Author: Francisco Silva Viana
Author-email: chicoviana12@hotmail.com
Project-URL: Bug Tracker, https://github.com/Eksoss/ncBuilder/issues
Classifier: Programming Language :: Python :: 3
Classifier: License :: OSI Approved :: MIT License
Classifier: Operating System :: OS Independent
Requires-Python: >=3.6
License-File: LICENSE.txt
Requires-Dist: numpy
Requires-Dist: pandas
Requires-Dist: netCDF4
